inspigtor/__init__.py
inspigtor/__pkginfo__.py
inspigtor/gui/__init__.py
inspigtor/gui/dialogs/__init__.py
inspigtor/gui/dialogs/dunn_matrix_dialog.py
inspigtor/gui/dialogs/group_averages_dialog.py
inspigtor/gui/dialogs/group_effect_dialog.py
inspigtor/gui/dialogs/group_medians_dialog.py
inspigtor/gui/dialogs/individual_averages_dialog.py
inspigtor/gui/dialogs/interval_settings_dialog.py
inspigtor/gui/dialogs/premortem_statistics_dialog.py
inspigtor/gui/dialogs/property_plotter_dialog.py
inspigtor/gui/dialogs/time_effect_dialog.py
inspigtor/gui/main_windows/__init__.py
inspigtor/gui/main_windows/main_window.py
inspigtor/gui/models/__init__.py
inspigtor/gui/models/pandas_data_model.py
inspigtor/gui/models/pigs_data_model.py
inspigtor/gui/models/pigs_groups_model.py
inspigtor/gui/models/pigs_pool_model.py
inspigtor/gui/models/pvalues_data_model.py
inspigtor/gui/models/workbook_data_model.py
inspigtor/gui/utils/__init__.py
inspigtor/gui/utils/helper_functions.py
inspigtor/gui/utils/navigation_toolbar.py
inspigtor/gui/views/__init__.py
inspigtor/gui/views/copy_pastable_tableview.py
inspigtor/gui/views/double_clickable_listview.py
inspigtor/gui/views/droppable_listview.py
inspigtor/gui/views/pigs_pool_listview.py
inspigtor/gui/widgets/__init__.py
inspigtor/gui/widgets/checkable_combobox.py
inspigtor/gui/widgets/coverages_widget.py
inspigtor/gui/widgets/interval_label.py
inspigtor/gui/widgets/intervals_widget.py
inspigtor/gui/widgets/logger_widget.py
inspigtor/gui/widgets/multiple_directories_selector.py
inspigtor/gui/widgets/statistics_widget.py
inspigtor/icons/export.ico
inspigtor/icons/inspigtor.icns
inspigtor/icons/inspigtor.png
inspigtor/kernel/__init__.py
inspigtor/kernel/pigs/__init__.py
inspigtor/kernel/pigs/pigs_groups.py
inspigtor/kernel/pigs/pigs_pool.py
inspigtor/kernel/readers/__init__.py
inspigtor/kernel/readers/picco2_reader.py
inspigtor/kernel/utils/__init__.py
inspigtor/kernel/utils/helper_functions.py
inspigtor/kernel/utils/progress_bar.py
inspigtor-0.0.9.dist-info/LICENSE
inspigtor-0.0.9.dist-info/METADATA
inspigtor-0.0.9.dist-info/WHEEL
inspigtor-0.0.9.dist-info/top_level.txt
inspigtor-0.0.9.dist-info/RECORD
