Metadata-Version: 2.1
Name: inspigtor
Version: 0.0.9
Summary: Analysis of physiological parameters taken from pig surgery
Home-page: UNKNOWN
Author: E.C. Pellegrini
Author-email: ericpellegrini76@gmail.com
Maintainer: E.C. Pellegrini
Maintainer-email: ericpellegrini76@gmail.com
License: GPL 3
Platform: Unix
Platform: Windows
Requires-Dist: matplotlib
Requires-Dist: numpy
Requires-Dist: pandas
Requires-Dist: PyQt5
Requires-Dist: scipy
Requires-Dist: scikit-posthocs
Requires-Dist: openpyxl
